bisect_find_first_bad.py
bisect_find_first_bad-0.0.4.dist-info/METADATA
bisect_find_first_bad-0.0.4.dist-info/WHEEL
bisect_find_first_bad-0.0.4.dist-info/top_level.txt
bisect_find_first_bad-0.0.4.dist-info/RECORD
