Metadata-Version: 2.1
Name: bisect-find-first-bad
Version: 0.0.4
Summary: tool like `git bisect run` but checks arbitrary options and not uses git to switch versions
Author-email: Alexander Rodionov <tandav@tandav.me>
Project-URL: source, https://github.com/tandav/bisect-find-first-bad
Project-URL: issues, https://github.com/tandav/bisect-find-first-bad/issues
Project-URL: release notes, https://github.com/tandav/bisect-find-first-bad/releases
Requires-Python: >=3.8
Provides-Extra: dev
Requires-Dist: bumpver ; extra == 'dev'
Requires-Dist: pre-commit ; extra == 'dev'
Requires-Dist: pytest ; extra == 'dev'
